mediafiregrabber/__init__.py
mediafiregrabber/cli.py
mediafiregrabber-1.4.dist-info/METADATA
mediafiregrabber-1.4.dist-info/WHEEL
mediafiregrabber-1.4.dist-info/entry_points.txt
mediafiregrabber-1.4.dist-info/top_level.txt
mediafiregrabber-1.4.dist-info/RECORD
