Metadata-Version: 2.1
Name: mediafiregrabber
Version: 1.4
Summary: Simple Python Package for MediaFire File Download and Information Retrieval
Home-page: https://github.com/swargarajbhowmik/mediafiregrabber
Author: Swargaraj Bhowmik
Author-email: contact@swargarajbhowmik.me
License: MIT
Requires-Dist: requests
Requires-Dist: beautifulsoup4
Requires-Dist: tqdm
Requires-Dist: urllib3
Requires-Dist: asyncio
Requires-Dist: aiohttp
